base_common/__init__.py
base_common/apps.py
base_common/context_processors.py
base_common/decorators.py
base_common/fields.py
base_common/middleware.py
base_common/models.py
base_common/signals.py
base_common/utils.py
base_common/migrations/__init__.py
base_common/templatetags/__init__.py
base_common/templatetags/json_extras.py
base_common-0.4.dist-info/LICENSE
base_common-0.4.dist-info/METADATA
base_common-0.4.dist-info/WHEEL
base_common-0.4.dist-info/top_level.txt
base_common-0.4.dist-info/RECORD
